affectlog/__init__.py
affectlog/_explanation.py
affectlog/_global_checks.py
affectlog/_global_utils.py
affectlog/_theme.py
affectlog/documentation.md
affectlog/_explainer/__init__.py
affectlog/_explainer/checks.py
affectlog/_explainer/helper.py
affectlog/_explainer/object.py
affectlog/_explainer/utils.py
affectlog/_explainer/yhat.py
affectlog/al360/__init__.py
affectlog/al360/_option_base.py
affectlog/al360/_plot_container.py
affectlog/al360/_plots_manager.py
affectlog/al360/_resource.py
affectlog/al360/_resource_manager.py
affectlog/al360/object.py
affectlog/al360/params.py
affectlog/al360/server.py
affectlog/al360/static.py
affectlog/al360/plots/__init__.py
affectlog/al360/plots/_accumulated_dependence_container.py
affectlog/al360/plots/_break_down_container.py
affectlog/al360/plots/_ceteris_paribus_container.py
affectlog/al360/plots/_fairness_check_container.py
affectlog/al360/plots/_feature_importance_container.py
affectlog/al360/plots/_metrics_container.py
affectlog/al360/plots/_partial_dependence_container.py
affectlog/al360/plots/_roc_container.py
affectlog/al360/plots/_shapley_values_container.py
affectlog/al360/plots/_shapley_values_dependence_container.py
affectlog/al360/plots/_shapley_values_variable_importance_container.py
affectlog/al360/plots/_variable_against_another_container.py
affectlog/al360/plots/_variable_distribution_container.py
affectlog/al360/resources/__init__.py
affectlog/al360/resources/_dataset_shapley_values_resource.py
affectlog/al360/resources/_shapley_values_resource.py
affectlog/aspect/__init__.py
affectlog/aspect/checks.py
affectlog/aspect/object.py
affectlog/aspect/plot.py
affectlog/aspect/utils.py
affectlog/aspect/_model_aspect_importance/__init__.py
affectlog/aspect/_model_aspect_importance/checks.py
affectlog/aspect/_model_aspect_importance/object.py
affectlog/aspect/_model_aspect_importance/plot.py
affectlog/aspect/_model_triplot/__init__.py
affectlog/aspect/_model_triplot/checks.py
affectlog/aspect/_model_triplot/object.py
affectlog-0.0.4.dist-info/LICENSE
affectlog-0.0.4.dist-info/METADATA
affectlog-0.0.4.dist-info/WHEEL
affectlog-0.0.4.dist-info/top_level.txt
affectlog-0.0.4.dist-info/RECORD
