Metadata-Version: 2.1
Name: affectlog
Version: 0.0.4
Summary: Trustworthy Machine Learning Assessment
Home-page: https://affectlog.com/
Author: AffectLog Developer Team
Author-email: developer@affectlog.com
Maintainer: AffectLog Developer Team
Maintainer-email: developer@affectlog.com
License: UNKNOWN
Project-URL: Documentation, https://affectlog.com/python/
Project-URL: Code, https://github.com/AffectLog360/AffectLog/tree/master/python/affectlog
Project-URL: Issue tracker, https://github.com/AffectLog360/AffectLog/issues
Platform: UNKNOWN
Classifier: Development Status :: 5 - Production/Stable
Classifier: Topic :: Scientific/Engineering
Classifier: Topic :: Scientific/Engineering :: Artificial Intelligence
Classifier: Programming Language :: Python :: 3
Classifier: Programming Language :: Python :: 3.8
Classifier: Programming Language :: Python :: 3.9
Classifier: Programming Language :: Python :: 3.10
Classifier: Programming Language :: Python :: 3.11
Classifier: License :: OSI Approved
Classifier: License :: OSI Approved :: GNU General Public License v3 (GPLv3)
Classifier: Operating System :: OS Independent
Requires-Python: >=3.8
License-File: LICENSE
Requires-Dist: setuptools
Requires-Dist: pandas >=1.5.0
Requires-Dist: numpy >=1.23.3
Requires-Dist: scipy >=1.6.3
Requires-Dist: plotly >=5.1.0
Requires-Dist: tqdm >=4.61.2
Provides-Extra: full
Requires-Dist: lime >=0.2.0.1 ; extra == 'full'
Requires-Dist: scikit-learn >=0.22.0 ; extra == 'full'
Requires-Dist: statsmodels >=0.11.1 ; extra == 'full'
Requires-Dist: shap >=0.35.0 ; extra == 'full'
Requires-Dist: flask >=1.1.2 ; extra == 'full'
Requires-Dist: flask-cors >=3.0.8 ; extra == 'full'
Requires-Dist: requests >=2.24.0 ; extra == 'full'
Requires-Dist: kaleido >=0.2.1 ; extra == 'full'
Requires-Dist: ppscore >=1.2.0 ; extra == 'full'
Requires-Dist: ipywidgets >=7.6.3 ; extra == 'full'
